[{"name": "光合作用", "type": "草系变化", "power": "0", "PP": "5", "effect": "回复自身一定的HP。"}, {"name": "水溅跃", "type": "普通魔法", "power": "20", "PP": "40", "effect": "给对方造成一定伤害。"}, {"name": "尾巴挠痒", "type": "普通变化", "power": "0", "PP": "30", "effect": "令对手的防御等级下降。"}, {"name": "猛烈撞击", "type": "普通物理", "power": "35", "PP": "35", "effect": "给对手造成较重的伤害。"}, {"name": "毒雾", "type": "毒系变化", "power": "0", "PP": "35", "effect": "让对手中毒。"}, {"name": "麻醉粉", "type": "草系变化", "power": "0", "PP": "30", "effect": "让对手麻醉。"}, {"name": "催眠粉", "type": "草系变化", "power": "0", "PP": "15", "effect": "一定机率让对手昏睡。"}, {"name": "种子机枪", "type": "草系物理", "power": "10", "PP": "30", "effect": "连续用种子攻击，给对手造成一定伤害。"}, {"name": "寄生种子", "type": "草系变化", "power": "0", "PP": "10", "effect": "在对手体内寄生一颗种子，每回合吸取一定HP。"}, {"name": "强力汲取", "type": "草系魔法", "power": "40", "PP": "15", "effect": "给对手造成一定伤害，同时回复一定HP。"}, {"name": "棉絮缠绕", "type": "草系变化", "power": "0", "PP": "40", "effect": "令对手速度等级下降。"}, {"name": "螺旋打击", "type": "虫系物理", "power": "70", "PP": "20", "effect": "连续地攻击对手，给对手造成一定伤害。"}, {"name": "清醒", "type": "草系变化", "power": "0", "PP": "10", "effect": "几回合内，睡眠免疫。"}, {"name": "超级汲取", "type": "草系魔法", "power": "100", "PP": "10", "effect": "给对手造成一定伤害，同时回复少量HP。"}, {"name": "飞跃打击", "type": "翼系魔法", "power": "110", "PP": "5", "effect": "本回合不受任何伤害，下回合发动攻击，一定机率让对手麻醉。先手+2"}, {"name": "临行留念", "type": "恶魔变化", "power": "0", "PP": "10", "effect": "令对手攻击和魔攻下降，使用后自身HP变为0。"}]