[{"name": "猛烈撞击", "type": "普通物理", "power": "35", "PP": "35", "effect": "给对手造成较重的伤害。"}, {"name": "滚石术", "type": "石系物理", "power": "50", "PP": "15", "effect": "给对方造成一定伤害。"}, {"name": "威慑", "type": "普通物理", "power": "40", "PP": "10", "effect": "见面第一回合使用，可以让对手恐惧。先手+1"}, {"name": "磁铁之力", "type": "机械物理", "power": "60", "PP": "20", "effect": "给对手造成一定伤害，100%命中。"}, {"name": "共振", "type": "普通变化", "power": "0", "PP": "40", "effect": "令对手魔抗等级下降。"}, {"name": "头槌爆", "type": "普通物理", "power": "30", "PP": "15", "effect": "提高防御等级，下回合连续攻击。"}, {"name": "破甲之爪", "type": "普通物理", "power": "75", "PP": "10", "effect": "一定机率让对方防御等级下降。"}, {"name": "蓄力", "type": "普通变化", "power": "0", "PP": "30", "effect": "提升自身暴击等级。"}, {"name": "星之雨", "type": "普通魔法", "power": "60", "PP": "20", "effect": "给对手造成一定伤害，100%命中。"}, {"name": "宝石之力", "type": "石系魔法", "power": "70", "PP": "20", "effect": "给对手造成一定伤害。"}, {"name": "疯狂攻击", "type": "普通物理", "power": "90", "PP": "20", "effect": "连续攻击敌人，之后自己陷入混乱状态。"}, {"name": "岩石爆", "type": "石系物理", "power": "100", "PP": "5", "effect": "提高暴击率。"}, {"name": "坚壁", "type": "石系物理", "power": "0", "PP": "5", "effect": "提升自身物理防御。"}, {"name": "石之伤", "type": "石系物理", "power": "120", "PP": "10", "effect": "给对手造成一定伤害，同时自己也受到一定伤害。"}]